funing/__init__.py
funing/settings.py
funing/settings4t.py
funing/settings4t.txt.py
funing/abc/__init__.py
funing/data/__init__.py
funing/data/cv2/LICENSE-3RD-PARTY.txt
funing/data/cv2/LICENSE.txt
funing/data/cv2/haarcascade_frontalface_default.xml
funing/data/templates/__init__.py
funing/data/templates/__pycache__/__init__.cpython-310.pyc
funing/locale/__init__.py
funing/locale/en_US/LC_MESSAGES/funing.mo
funing/locale/zh_CN/LC_MESSAGES/funing.mo
funing/media/__init__.py
funing/path/__init__.py
funing/widgets/__init__.py
funing/widgets/abc.py
funing/widgets/about.py
funing/widgets/bottom.py
funing/widgets/color_common.py
funing/widgets/common.py
funing/widgets/enum.py
funing/widgets/frame.py
funing/widgets/info.py
funing/widgets/main.py
funing/widgets/seperator.py
funing/widgets/top.py
venv/bin/activate_this.py
venv/bin/rst2html.py
venv/bin/rst2html4.py
venv/bin/rst2html5.py
venv/bin/rst2latex.py
venv/bin/rst2man.py
venv/bin/rst2odt.py
venv/bin/rst2odt_prepstyles.py
venv/bin/rst2pseudoxml.py
venv/bin/rst2s5.py
venv/bin/rst2xetex.py
venv/bin/rst2xml.py
venv/bin/rstpep2html.py
funing-0.2.65.dist-info/LICENSE
funing-0.2.65.dist-info/METADATA
funing-0.2.65.dist-info/WHEEL
funing-0.2.65.dist-info/entry_points.txt
funing-0.2.65.dist-info/top_level.txt
funing-0.2.65.dist-info/RECORD
